mcp_toolkit_wrapper/__init__.py
mcp_toolkit_wrapper/installer.py
mcp_toolkit_wrapper/bin/mcp-toolkit
mcp_sandbox_toolkit-1.8.0.dist-info/METADATA
mcp_sandbox_toolkit-1.8.0.dist-info/WHEEL
mcp_sandbox_toolkit-1.8.0.dist-info/entry_points.txt
mcp_sandbox_toolkit-1.8.0.dist-info/licenses/LICENSE
mcp_sandbox_toolkit-1.8.0.dist-info/licenses/NOTICE
mcp_sandbox_toolkit-1.8.0.dist-info/RECORD
