Metadata-Version: 2.4
Name: mcp-sandbox-toolkit
Version: 1.8.0
Summary: A cross-platform sandboxed file system operations toolkit based on Model Context Protocol (MCP)
Project-URL: Homepage, https://github.com/shibingli/mcp-toolkit
Project-URL: Documentation, https://github.com/shibingli/mcp-toolkit/blob/main/README.md
Project-URL: Repository, https://github.com/shibingli/mcp-toolkit
Project-URL: Issues, https://github.com/shibingli/mcp-toolkit/issues
Project-URL: Changelog, https://github.com/shibingli/mcp-toolkit/releases
Author-email: MCP Toolkit Authors <shibingli@yeah.net>
License: Apache-2.0
License-File: LICENSE
License-File: NOTICE
Keywords: file-system,mcp,model-context-protocol,sandbox,toolkit
Classifier: Development Status :: 4 - Beta
Classifier: Intended Audience :: Developers
Classifier: License :: OSI Approved :: Apache Software License
Classifier: Operating System :: OS Independent
Classifier: Programming Language :: Python :: 3
Classifier: Programming Language :: Python :: 3.8
Classifier: Programming Language :: Python :: 3.9
Classifier: Programming Language :: Python :: 3.10
Classifier: Programming Language :: Python :: 3.11
Classifier: Programming Language :: Python :: 3.12
Classifier: Topic :: Software Development :: Libraries
Classifier: Topic :: System :: Filesystems
Requires-Python: >=3.8
